run_weeklychallenge.py
run_weeklychallenge-1.0.6.dist-info/licenses/LICENSE
run_weeklychallenge-1.0.6.dist-info/METADATA
run_weeklychallenge-1.0.6.dist-info/WHEEL
run_weeklychallenge-1.0.6.dist-info/top_level.txt
run_weeklychallenge-1.0.6.dist-info/RECORD
