Metadata-Version: 2.4
Name: run_weeklychallenge
Version: 1.0.6
Summary: Facilitates running a solution to https://theweeklychallenge.org using one or more sets of inputs provided as JSON command line arguments.
Author-email: Yitzchak Scott-Thoennes <yitzchakscottthoennes@gmail.com>
License-Expression: MIT
Project-URL: Homepage, https://github.com/ysth/runweeklychallenge-py
Project-URL: Issues, https://github.com/ysth/runweeklychallenge-py/issues
Classifier: Programming Language :: Python :: 3
Classifier: Operating System :: OS Independent
Requires-Python: >=3.9
License-File: LICENSE
Dynamic: license-file
